LICENSE
README.md
pyproject.toml
setup.cfg
setup.py
evshell/Piraha.py
evshell/__init__.py
evshell/colored.py
evshell/completer.py
evshell/here.py
evshell/myshell.py
evshell/pipe_threads.py
evshell/reaper.py
evshell/test.py
evshell/tmpfile.py
evshell/version.py
evshell.egg-info/PKG-INFO
evshell.egg-info/SOURCES.txt
evshell.egg-info/dependency_links.txt
evshell.egg-info/entry_points.txt
evshell.egg-info/requires.txt
evshell.egg-info/top_level.txt
images/sshell-logo.png
notebooks/demo.ipynb
pieshell/version.py
tests/a.sh
tests/b.sh
tests/case.sh
tests/cat.sh
tests/denied.sh
tests/fib.sh
tests/foo.sh
tests/foo2.sh
tests/foo3.sh
tests/h.sh
tests/pipe.sh
tests/pipes2.sh
tests/rmback.sh
tests/testm.sh
tests/testr.sh
tests/testss.sh
tests/x.py
tests/x.sh