Metadata-Version: 2.1
Name: evshell
Version: 0.0.18
Summary: evshell: The Everglades Shell, an implementation of the shell in pure Python
Home-page: https://github.com/stevenrbrandt/evshell.git
Author: Steven R. Brandt
Author-email: steven@stevenrbrandt.com
License: LGPL
License-File: LICENSE
